edc_export/__init__.py
edc_export/admin_site.py
edc_export/apps.py
edc_export/archive_exporter.py
edc_export/auth_objects.py
edc_export/auths.py
edc_export/choices.py
edc_export/constants.py
edc_export/exceptions.py
edc_export/exportables.py
edc_export/files_archiver.py
edc_export/files_emailer.py
edc_export/managers.py
edc_export/model_options.py
edc_export/navbars.py
edc_export/offline_models.py
edc_export/system_checks.py
edc_export/urls.py
edc_export/utils.py
edc_export/admin/__init__.py
edc_export/admin/data_request_admin.py
edc_export/admin/data_request_history_admin.py
edc_export/admin/export_receipt_admin.py
edc_export/admin/file_history_admin.py
edc_export/admin/object_history_admin.py
edc_export/admin/plan_admin.py
edc_export/admin/upload_export_receipt_file_admin.py
edc_export/forms/__init__.py
edc_export/forms/data_request_form.py
edc_export/management/__init__.py
edc_export/management/commands/__init__.py
edc_export/management/commands/export_object_history.py
edc_export/management/commands/import_receipts.py
edc_export/migrations/0001_initial.py
edc_export/migrations/0002_auto_20180922_1843.py
edc_export/migrations/0003_auto_20181108_0353.py
edc_export/migrations/0004_auto_20190305_0123.py
edc_export/migrations/0005_exportdata_importdata.py
edc_export/migrations/0006_auto_20200512_0208.py
edc_export/migrations/0007_auto_20200512_0452.py
edc_export/migrations/0008_auto_20201002_0403.py
edc_export/migrations/0009_auto_20210510_2036.py
edc_export/migrations/0010_auto_20210910_1636.py
edc_export/migrations/0011_auto_20220215_2308.py
edc_export/migrations/0012_auto_20220704_1841.py
edc_export/migrations/0013_edcpermissions.py
edc_export/migrations/0014_alter_plan_options.py
edc_export/migrations/0015_alter_datarequest_managers_and_more.py
edc_export/migrations/0016_alter_datarequest_device_created_and_more.py
edc_export/migrations/0017_alter_datarequest_options_and_more.py
edc_export-1.0.4.dist-info/licenses/AUTHORS.rst
edc_export-1.0.4.dist-info/licenses/LICENSE
edc_export-1.0.4.dist-info/METADATA
edc_export-1.0.4.dist-info/WHEEL
edc_export-1.0.4.dist-info/top_level.txt
edc_export-1.0.4.dist-info/RECORD
